yivy/__init__.py
yivy/core.py
yivy/mobile.py
yivy/widgets.py
yivy-1.0.0.dist-info/METADATA
yivy-1.0.0.dist-info/WHEEL
yivy-1.0.0.dist-info/top_level.txt
yivy-1.0.0.dist-info/RECORD
