Metadata-Version: 2.2
Name: yivy
Version: 1.0.0
Summary: A simple and powerful GUI library for desktop and mobile.
Author: YangHoujing
Author-email: your.email@example.com
Classifier: Programming Language :: Python :: 3
Classifier: License :: OSI Approved :: MIT License
Classifier: Operating System :: OS Independent
Requires-Python: >=3.6
Requires-Dist: kivy>=2.0.0
Dynamic: author
Dynamic: author-email
Dynamic: classifier
Dynamic: requires-dist
Dynamic: requires-python
Dynamic: summary
